<?xml version="1.0"?>
<product xmlns:xsi="http://www.w3.org/2001/XMLSchema-instance" version="v1.7.1" xsi:noNamespaceSchemaLocation="http://www.bom.gov.au/schema/v1.7/product.xsd">
  <amoc>
    <source>
      <sender>Australian Government Bureau of Meteorology</sender>
      <region>Victoria</region>
      <office>VICRO</office>
      <copyright>http://www.bom.gov.au/other/copyright.shtml</copyright>
      <disclaimer>http://www.bom.gov.au/other/disclaimer.shtml</disclaimer>
    </source>
    <identifier>IDV60920</identifier>
    <issue-time-utc>2024-04-28T17:41:05+00:00</issue-time-utc>
    <issue-time-local tz="EST">2024-04-29T03:41:05+10:00</issue-time-local>
    <sent-time>2024-04-28T17:42:39+00:00</sent-time>
    <status>O</status>
    <service>WSP</service>
    <product-type>O</product-type>
    <phase>NEW</phase>
  </amoc>
  <observations>
    <station wmo-id="95936" bom-id="086338" tz="Australia/Melbourne" stn-name="MELBOURNE (OLYMPIC PARK)" stn-height="7.53" type="AWS" lat="-37.8255" lon="144.9816" forecast-district-id="VIC_PW007" description="Melbourne (Olympic Park)">
      <period index="0" time-utc="2024-04-28T17:40:00+00:00" time-local="2024-04-29T03:40:00+10:00" wind-src="OMD">
        <level index="0" type="surface">
          <element units="Celsius" type="apparent_temp">11.2</element>
          <element units="Celsius" type="delta_t">2.8</element>
          <element units="km/h" type="gust_kmh">0</element>
          <element units="knots" type="wind_gust_spd">0</element>
          <element units="Celsius" type="air_temperature">12.1</element>
          <element units="Celsius" type="dew_point">6.2</element>
          <element units="hPa" type="pres">1018.8</element>
          <element units="hPa" type="msl_pres">1018.8</element>
          <element units="hPa" type="qnh_pres">1018.8</element>
          <element units="%" type="rel-humidity">67</element>
          <element units="km" type="vis_km">52</element>
          <element type="wind_dir">CALM</element>
          <element units="deg" type="wind_dir_deg">0</element>
          <element units="km/h" type="wind_spd_kmh">0</element>
          <element units="knots" type="wind_spd">0</element>
          <element start-time-local="2024-04-28T09:00:00+10:00" end-time-local="2024-04-29T03:42:00+10:00" duration="1122" start-time-utc="2024-04-27T23:00:00+00:00" end-time-utc="2024-04-28T17:42:00+00:00" units="mm" type="rainfall">0.0</element>
          <element start-time-local="2024-04-27T09:00:00+10:00" end-time-local="2024-04-28T09:00:00+10:00" duration="1440" start-time-utc="2024-04-26T23:00:00+00:00" end-time-utc="2024-04-27T23:00:00+00:00" units="mm" type="rainfall_24hr">0.0</element>
          <element start-time-local="2024-04-28T06:00:00+10:00" end-time-local="2024-04-28T21:00:00+10:00" start-time-utc="2024-04-27T20:00:00+00:00" end-time-utc="2024-04-28T11:00:00+00:00" units="Celsius" type="maximum_air_temperature" instance="running" time-utc="2024-04-28T05:42:00+00:00" time-local="2024-04-28T15:42:00+10:00">22.6</element>
          <element start-time-local="2024-04-28T18:00:00+10:00" end-time-local="2024-04-29T09:00:00+10:00" start-time-utc="2024-04-28T08:00:00+00:00" end-time-utc="2024-04-28T23:00:00+00:00" units="Celsius" type="minimum_air_temperature" instance="running" time-utc="2024-04-28T17:15:00+00:00" time-local="2024-04-29T03:15:00+10:00">11.5</element>
          <element start-time-local="2024-04-29T00:00:00+10:00" end-time-local="2024-04-30T00:00:00+10:00" start-time-utc="2024-04-28T14:00:00+00:00" end-time-utc="2024-04-29T14:00:00+00:00" units="knots" type="maximum_gust_spd" instance="running" time-utc="2024-04-28T15:10:00+00:00" time-local="2024-04-29T01:10:00+10:00">9</element>
          <element start-time-local="2024-04-29T00:00:00+10:00" end-time-local="2024-04-30T00:00:00+10:00" start-time-utc="2024-04-28T14:00:00+00:00" end-time-utc="2024-04-29T14:00:00+00:00" units="km/h" type="maximum_gust_kmh" instance="running" time-utc="2024-04-28T15:10:00+00:00" time-local="2024-04-29T01:10:00+10:00">17</element>
          <element start-time-local="2024-04-29T00:00:00+10:00" end-time-local="2024-04-30T00:00:00+10:00" start-time-utc="2024-04-28T14:00:00+00:00" end-time-utc="2024-04-29T14:00:00+00:00" type="maximum_gust_dir" instance="running" time-utc="2024-04-28T15:10:00+00:00" time-local="2024-04-29T01:10:00+10:00">N</element>
        </level>
      </period>
    </station>
    <station wmo-id="94866" bom-id="086282" tz="Australia/Melbourne" stn-name="MELBOURNE AIRPORT" stn-height="113.40" type="AWS" lat="-37.6654" lon="144.8322" forecast-district-id="VIC_PW007" description="Melbourne Airport">
      <period index="0" time-utc="2024-04-28T17:40:00+00:00" time-local="2024-04-29T03:40:00+10:00" wind-src="OMD">
        <level index="0" type="surface">
          <element units="Celsius" type="apparent_temp">8.7</element>
          <element type="cloud">Mostly clear</element>
          <element type="cloud_oktas">1</element>
          <element units="Celsius" type="delta_t">4.3</element>
          <element units="km/h" type="gust_kmh">19</element>
          <element units="knots" type="wind_gust_spd">10</element>
          <element units="Celsius" type="air_temperature">13.3</element>
          <element units="Celsius" type="dew_point">3.7</element>
          <element units="hPa" type="pres">1018.8</element>
          <element units="hPa" type="msl_pres">1018.8</element>
          <element units="hPa" type="qnh_pres">1018.9</element>
          <element units="%" type="rel-humidity">52</element>
          <element units="km" type="vis_km">72</element>
          <element type="wind_dir">NE</element>
          <element units="deg" type="wind_dir_deg">38</element>
          <element units="km/h" type="wind_spd_kmh">17</element>
          <element units="knots" type="wind_spd">9</element>
          <element start-time-local="2024-04-28T09:00:00+10:00" end-time-local="2024-04-29T03:42:00+10:00" duration="1122" start-time-utc="2024-04-27T23:00:00+00:00" end-time-utc="2024-04-28T17:42:00+00:00" units="mm" type="rainfall">0.0</element>
          <element start-time-local="2024-04-27T09:00:00+10:00" end-time-local="2024-04-28T09:00:00+10:00" duration="1440" start-time-utc="2024-04-26T23:00:00+00:00" end-time-utc="2024-04-27T23:00:00+00:00" units="mm" type="rainfall_24hr">0.0</element>
          <element start-time-local="2024-04-28T06:00:00+10:00" end-time-local="2024-04-28T21:00:00+10:00" start-time-utc="2024-04-27T20:00:00+00:00" end-time-utc="2024-04-28T11:00:00+00:00" units="Celsius" type="maximum_air_temperature" instance="running" time-utc="2024-04-28T05:37:00+00:00" time-local="2024-04-28T15:37:00+10:00">22.5</element>
          <element start-time-local="2024-04-28T18:00:00+10:00" end-time-local="2024-04-29T09:00:00+10:00" start-time-utc="2024-04-28T08:00:00+00:00" end-time-utc="2024-04-28T23:00:00+00:00" units="Celsius" type="minimum_air_temperature" instance="running" time-utc="2024-04-28T13:56:00+00:00" time-local="2024-04-28T23:56:00+10:00">11.4</element>
          <element start-time-local="2024-04-29T00:00:00+10:00" end-time-local="2024-04-30T00:00:00+10:00" start-time-utc="2024-04-28T14:00:00+00:00" end-time-utc="2024-04-29T14:00:00+00:00" units="knots" type="maximum_gust_spd" instance="running" time-utc="2024-04-28T15:20:00+00:00" time-local="2024-04-29T01:20:00+10:00">18</element>
          <element start-time-local="2024-04-29T00:00:00+10:00" end-time-local="2024-04-30T00:00:00+10:00" start-time-utc="2024-04-28T14:00:00+00:00" end-time-utc="2024-04-29T14:00:00+00:00" units="km/h" type="maximum_gust_kmh" instance="running" time-utc="2024-04-28T15:20:00+00:00" time-local="2024-04-29T01:20:00+10:00">33</element>
          <element start-time-local="2024-04-29T00:00:00+10:00" end-time-local="2024-04-30T00:00:00+10:00" start-time-utc="2024-04-28T14:00:00+00:00" end-time-utc="2024-04-29T14:00:00+00:00" type="maximum_gust_dir" instance="running" time-utc="2024-04-28T15:20:00+00:00" time-local="2024-04-29T01:20:00+10:00">NNW</element>
        </level>
      </period>
    </station>
    <station wmo-id="94854" bom-id="087113" tz="Australia/Melbourne" stn-name="AVALON AIRPORT" stn-height="10.60" type="AWS" lat="-38.0288" lon="144.4783" forecast-district-id="VIC_PW007" description="Avalon">
      <period index="0" time-utc="2024-04-28T17:40:00+00:00" time-local="2024-04-29T03:40:00+10:00" wind-src="OMD">
        <level index="0" type="surface">
          <element units="Celsius" type="apparent_temp">12.6</element>
          <element type="cloud">Mostly clear</element>
          <element type="cloud_oktas">2</element>
          <element units="Celsius" type="delta_t">6.8</element>
          <element units="km/h" type="gust_kmh">17</element>
          <element units="knots" type="wind_gust_spd">9</element>
          <element units="Celsius" type="air_temperature">17.1</element>
          <element units="Celsius" type="dew_point">1.9</element>
          <element units="hPa" type="pres">1018.1</element>
          <element units="hPa" type="msl_pres">1018.1</element>
          <element units="hPa" type="qnh_pres">1018.1</element>
          <element units="%" type="rel-humidity">36</element>
          <element units="km" type="vis_km">58</element>
          <element type="wind_dir">WNW</element>
          <element units="deg" type="wind_dir_deg">300</element>
          <element units="km/h" type="wind_spd_kmh">15</element>
          <element units="knots" type="wind_spd">8</element>
          <element start-time-local="2024-04-28T09:00:00+10:00" end-time-local="2024-04-29T03:42:00+10:00" duration="1122" start-time-utc="2024-04-27T23:00:00+00:00" end-time-utc="2024-04-28T17:42:00+00:00" units="mm" type="rainfall">0.0</element>
          <element start-time-local="2024-04-27T09:00:00+10:00" end-time-local="2024-04-28T09:00:00+10:00" duration="1440" start-time-utc="2024-04-26T23:00:00+00:00" end-time-utc="2024-04-27T23:00:00+00:00" units="mm" type="rainfall_24hr">0.0</element>
          <element start-time-local="2024-04-28T06:00:00+10:00" end-time-local="2024-04-28T21:00:00+10:00" start-time-utc="2024-04-27T20:00:00+00:00" end-time-utc="2024-04-28T11:00:00+00:00" units="Celsius" type="maximum_air_temperature" instance="running" time-utc="2024-04-28T04:48:00+00:00" time-local="2024-04-28T14:48:00+10:00">23.4</element>
          <element start-time-local="2024-04-28T18:00:00+10:00" end-time-local="2024-04-29T09:00:00+10:00" start-time-utc="2024-04-28T08:00:00+00:00" end-time-utc="2024-04-28T23:00:00+00:00" units="Celsius" type="minimum_air_temperature" instance="running" time-utc="2024-04-28T15:12:00+00:00" time-local="2024-04-29T01:12:00+10:00">12.4</element>
          <element start-time-local="2024-04-29T00:00:00+10:00" end-time-local="2024-04-30T00:00:00+10:00" start-time-utc="2024-04-28T14:00:00+00:00" end-time-utc="2024-04-29T14:00:00+00:00" units="knots" type="maximum_gust_spd" instance="running" time-utc="2024-04-28T15:32:00+00:00" time-local="2024-04-29T01:32:00+10:00">15</element>
          <element start-time-local="2024-04-29T00:00:00+10:00" end-time-local="2024-04-30T00:00:00+10:00" start-time-utc="2024-04-28T14:00:00+00:00" end-time-utc="2024-04-29T14:00:00+00:00" units="km/h" type="maximum_gust_kmh" instance="running" time-utc="2024-04-28T15:32:00+00:00" time-local="2024-04-29T01:32:00+10:00">28</element>
          <element start-time-local="2024-04-29T00:00:00+10:00" end-time-local="2024-04-30T00:00:00+10:00" start-time-utc="2024-04-28T14:00:00+00:00" end-time-utc="2024-04-29T14:00:00+00:00" type="maximum_gust_dir" instance="running" time-utc="2024-04-28T15:32:00+00:00" time-local="2024-04-29T01:32:00+10:00">NW</element>
        </level>
      </period>
    </station>
    <station wmo-id="94898" bom-id="086361" tz="Australia/Melbourne" stn-name="CERBERUS" stn-height="12.69" type="AWS" lat="-38.3646" lon="145.1785" forecast-district-id="VIC_PW007" description="Cerberus">
      <period index="0" time-utc="2024-04-28T17:40:00+00:00" time-local="2024-04-29T03:40:00+10:00" wind-src="OMD">
        <level index="0" type="surface">
          <element units="Celsius" type="apparent_temp">13.0</element>
          <element units="Celsius" type="delta_t">4.8</element>
          <element units="km/h" type="gust_kmh">9</element>
          <element units="knots" type="wind_gust_spd">5</element>
          <element units="Celsius" type="air_temperature">15.4</element>
          <element units="Celsius" type="dew_point">5.3</element>
          <element units="hPa" type="pres">1017.9</element>
          <element units="hPa" type="msl_pres">1017.9</element>
          <element units="%" type="rel-humidity">51</element>
          <element type="wind_dir">NNW</element>
          <element units="deg" type="wind_dir_deg">344</element>
          <element units="km/h" type="wind_spd_kmh">7</element>
          <element units="knots" type="wind_spd">4</element>
          <element start-time-local="2024-04-28T09:00:00+10:00" end-time-local="2024-04-29T03:42:00+10:00" duration="1122" start-time-utc="2024-04-27T23:00:00+00:00" end-time-utc="2024-04-28T17:42:00+00:00" units="mm" type="rainfall">0.0</element>
          <element start-time-local="2024-04-27T09:00:00+10:00" end-time-local="2024-04-28T09:00:00+10:00" duration="1440" start-time-utc="2024-04-26T23:00:00+00:00" end-time-utc="2024-04-27T23:00:00+00:00" units="mm" type="rainfall_24hr">0.2</element>
          <element start-time-local="2024-04-28T06:00:00+10:00" end-time-local="2024-04-28T21:00:00+10:00" start-time-utc="2024-04-27T20:00:00+00:00" end-time-utc="2024-04-28T11:00:00+00:00" units="Celsius" type="maximum_air_temperature" instance="running" time-utc="2024-04-28T05:01:00+00:00" time-local="2024-04-28T15:01:00+10:00">22.2</element>
          <element start-time-local="2024-04-28T18:00:00+10:00" end-time-local="2024-04-29T09:00:00+10:00" start-time-utc="2024-04-28T08:00:00+00:00" end-time-utc="2024-04-28T23:00:00+00:00" units="Celsius" type="minimum_air_temperature" instance="running" time-utc="2024-04-28T10:53:00+00:00" time-local="2024-04-28T20:53:00+10:00">9.6</element>
          <element start-time-local="2024-04-29T00:00:00+10:00" end-time-local="2024-04-30T00:00:00+10:00" start-time-utc="2024-04-28T14:00:00+00:00" end-time-utc="2024-04-29T14:00:00+00:00" units="knots" type="maximum_gust_spd" instance="running" time-utc="2024-04-28T16:36:00+00:00" time-local="2024-04-29T02:36:00+10:00">8</element>
          <element start-time-local="2024-04-29T00:00:00+10:00" end-time-local="2024-04-30T00:00:00+10:00" start-time-utc="2024-04-28T14:00:00+00:00" end-time-utc="2024-04-29T14:00:00+00:00" units="km/h" type="maximum_gust_kmh" instance="running" time-utc="2024-04-28T16:36:00+00:00" time-local="2024-04-29T02:36:00+10:00">15</element>
          <element start-time-local="2024-04-29T00:00:00+10:00" end-time-local="2024-04-30T00:00:00+10:00" start-time-utc="2024-04-28T14:00:00+00:00" end-time-utc="2024-04-29T14:00:00+00:00" type="maximum_gust_dir" instance="running" time-utc="2024-04-28T16:36:00+00:00" time-local="2024-04-29T02:36:00+10:00">NW</element>
        </level>
      </period>
    </station>
    <station wmo-id="94864" bom-id="086383" tz="Australia/Melbourne" stn-name="COLDSTREAM" stn-height="83.00" type="AWS" lat="-37.7239" lon="145.4092" forecast-district-id="VIC_PW007" description="Coldstream">
      <period index="0" time-utc="2024-04-28T17:40:00+00:00" time-local="2024-04-29T03:40:00+10:00" wind-src="OMD">
        <level index="0" type="surface">
          <element units="Celsius" type="apparent_temp">4.0</element>
          <element units="Celsius" type="delta_t">0.0</element>
          <element units="km/h" type="gust_kmh">0</element>
          <element units="knots" type="wind_gust_spd">0</element>
          <element units="Celsius" type="air_temperature">5.1</element>
          <element units="Celsius" type="dew_point">5.0</element>
          <element units="hPa" type="pres">1019.1</element>
          <element units="hPa" type="msl_pres">1019.1</element>
          <element units="hPa" type="qnh_pres">1019.2</element>
          <element units="%" type="rel-humidity">99</element>
          <element type="wind_dir">CALM</element>
          <element units="deg" type="wind_dir_deg">0</element>
          <element units="km/h" type="wind_spd_kmh">0</element>
          <element units="knots" type="wind_spd">0</element>
          <element start-time-local="2024-04-28T09:00:00+10:00" end-time-local="2024-04-29T03:42:00+10:00" duration="1122" start-time-utc="2024-04-27T23:00:00+00:00" end-time-utc="2024-04-28T17:42:00+00:00" units="mm" type="rainfall">0.0</element>
          <element start-time-local="2024-04-27T09:00:00+10:00" end-time-local="2024-04-28T09:00:00+10:00" duration="1440" start-time-utc="2024-04-26T23:00:00+00:00" end-time-utc="2024-04-27T23:00:00+00:00" units="mm" type="rainfall_24hr">0.0</element>
          <element start-time-local="2024-04-28T06:00:00+10:00" end-time-local="2024-04-28T21:00:00+10:00" start-time-utc="2024-04-27T20:00:00+00:00" end-time-utc="2024-04-28T11:00:00+00:00" units="Celsius" type="maximum_air_temperature" instance="running" time-utc="2024-04-28T05:38:00+00:00" time-local="2024-04-28T15:38:00+10:00">22.1</element>
          <element start-time-local="2024-04-28T18:00:00+10:00" end-time-local="2024-04-29T09:00:00+10:00" start-time-utc="2024-04-28T08:00:00+00:00" end-time-utc="2024-04-28T23:00:00+00:00" units="Celsius" type="minimum_air_temperature" instance="running" time-utc="2024-04-28T17:40:00+00:00" time-local="2024-04-29T03:40:00+10:00">5.1</element>
          <element start-time-local="2024-04-29T00:00:00+10:00" end-time-local="2024-04-30T00:00:00+10:00" start-time-utc="2024-04-28T14:00:00+00:00" end-time-utc="2024-04-29T14:00:00+00:00" units="knots" type="maximum_gust_spd" instance="running" time-utc="2024-04-28T16:20:00+00:00" time-local="2024-04-29T02:20:00+10:00">7</element>
          <element start-time-local="2024-04-29T00:00:00+10:00" end-time-local="2024-04-30T00:00:00+10:00" start-time-utc="2024-04-28T14:00:00+00:00" end-time-utc="2024-04-29T14:00:00+00:00" units="km/h" type="maximum_gust_kmh" instance="running" time-utc="2024-04-28T16:20:00+00:00" time-local="2024-04-29T02:20:00+10:00">13</element>
          <element start-time-local="2024-04-29T00:00:00+10:00" end-time-local="2024-04-30T00:00:00+10:00" start-time-utc="2024-04-28T14:00:00+00:00" end-time-utc="2024-04-29T14:00:00+00:00" type="maximum_gust_dir" instance="running" time-utc="2024-04-28T16:20:00+00:00" time-local="2024-04-29T02:20:00+10:00">SSW</element>
        </level>
      </period>
    </station>
    <station wmo-id="95866" bom-id="086038" tz="Australia/Melbourne" stn-name="ESSENDON AIRPORT" stn-height="78.40" type="AWS" lat="-37.7276" lon="144.9066" forecast-district-id="VIC_PW007" description="Essendon Airport">
      <period index="0" time-utc="2024-04-28T17:40:00+00:00" time-local="2024-04-29T03:40:00+10:00" wind-src="OMD">
        <level index="0" type="surface">
          <element units="Celsius" type="apparent_temp">10.9</element>
          <element type="cloud">Mostly clear</element>
          <element type="cloud_oktas">1</element>
          <element units="Celsius" type="delta_t">4.4</element>
          <element units="km/h" type="gust_kmh">11</element>
          <element units="knots" type="wind_gust_spd">6</element>
          <element units="Celsius" type="air_temperature">13.9</element>
          <element units="Celsius" type="dew_point">4.2</element>
          <element units="hPa" type="pres">1018.6</element>
          <element units="hPa" type="msl_pres">1018.6</element>
          <element units="hPa" type="qnh_pres">1018.7</element>
          <element units="%" type="rel-humidity">52</element>
          <element units="km" type="vis_km">50</element>
          <element units="deg" type="wind_dir_deg">0</element>
          <element units="km/h" type="wind_spd_kmh">9</element>
          <element units="knots" type="wind_spd">5</element>
          <element start-time-local="2024-04-28T09:00:00+10:00" end-time-local="2024-04-29T03:42:00+10:00" duration="1122" start-time-utc="2024-04-27T23:00:00+00:00" end-time-utc="2024-04-28T17:42:00+00:00" units="mm" type="rainfall">0.0</element>
          <element start-time-local="2024-04-27T09:00:00+10:00" end-time-local="2024-04-28T09:00:00+10:00" duration="1440" start-time-utc="2024-04-26T23:00:00+00:00" end-time-utc="2024-04-27T23:00:00+00:00" units="mm" type="rainfall_24hr">0.0</element>
          <element start-time-local="2024-04-28T06:00:00+10:00" end-time-local="2024-04-28T21:00:00+10:00" start-time-utc="2024-04-27T20:00:00+00:00" end-time-utc="2024-04-28T11:00:00+00:00" units="Celsius" type="maximum_air_temperature" instance="running" time-utc="2024-04-28T06:00:00+00:00" time-local="2024-04-28T16:00:00+10:00">22.5</element>
          <element start-time-local="2024-04-28T18:00:00+10:00" end-time-local="2024-04-29T09:00:00+10:00" start-time-utc="2024-04-28T08:00:00+00:00" end-time-utc="2024-04-28T23:00:00+00:00" units="Celsius" type="minimum_air_temperature" instance="running" time-utc="2024-04-28T13:22:00+00:00" time-local="2024-04-28T23:22:00+10:00">13.1</element>
          <element start-time-local="2024-04-29T00:00:00+10:00" end-time-local="2024-04-30T00:00:00+10:00" start-time-utc="2024-04-28T14:00:00+00:00" end-time-utc="2024-04-29T14:00:00+00:00" units="knots" type="maximum_gust_spd" instance="running" time-utc="2024-04-28T15:27:00+00:00" time-local="2024-04-29T01:27:00+10:00">12</element>
          <element start-time-local="2024-04-29T00:00:00+10:00" end-time-local="2024-04-30T00:00:00+10:00" start-time-utc="2024-04-28T14:00:00+00:00" end-time-utc="2024-04-29T14:00:00+00:00" units="km/h" type="maximum_gust_kmh" instance="running" time-utc="2024-04-28T15:27:00+00:00" time-local="2024-04-29T01:27:00+10:00">22</element>
          <element start-time-local="2024-04-29T00:00:00+10:00" end-time-local="2024-04-30T00:00:00+10:00" start-time-utc="2024-04-28T14:00:00+00:00" end-time-utc="2024-04-29T14:00:00+00:00" type="maximum_gust_dir" instance="running" time-utc="2024-04-28T15:27:00+00:00" time-local="2024-04-29T01:27:00+10:00">NNW</element>
        </level>
      </period>
    </station>
    <station wmo-id="95872" bom-id="086376" tz="Australia/Melbourne" stn-name="FAWKNER BEACON" stn-height="17.00" type="AWS" lat="-37.9483" lon="144.9269" forecast-district-id="VIC_MW005" description="Fawkner Beacon">
      <period index="0" time-utc="2024-04-28T17:40:00+00:00" time-local="2024-04-29T03:40:00+10:00" wind-src="OMD">
        <level index="0" type="surface">
          <element units="km/h" type="gust_kmh">22</element>
          <element units="knots" type="wind_gust_spd">12</element>
          <element type="wind_dir">N</element>
          <element units="deg" type="wind_dir_deg">359</element>
          <element units="km/h" type="wind_spd_kmh">20</element>
          <element units="knots" type="wind_spd">11</element>
          <element start-time-local="2024-04-29T00:00:00+10:00" end-time-local="2024-04-30T00:00:00+10:00" start-time-utc="2024-04-28T14:00:00+00:00" end-time-utc="2024-04-29T14:00:00+00:00" units="knots" type="maximum_gust_spd" instance="running" time-utc="2024-04-28T16:31:00+00:00" time-local="2024-04-29T02:31:00+10:00">15</element>
          <element start-time-local="2024-04-29T00:00:00+10:00" end-time-local="2024-04-30T00:00:00+10:00" start-time-utc="2024-04-28T14:00:00+00:00" end-time-utc="2024-04-29T14:00:00+00:00" units="km/h" type="maximum_gust_kmh" instance="running" time-utc="2024-04-28T16:31:00+00:00" time-local="2024-04-29T02:31:00+10:00">28</element>
          <element start-time-local="2024-04-29T00:00:00+10:00" end-time-local="2024-04-30T00:00:00+10:00" start-time-utc="2024-04-28T14:00:00+00:00" end-time-utc="2024-04-29T14:00:00+00:00" type="maximum_gust_dir" instance="running" time-utc="2024-04-28T16:31:00+00:00" time-local="2024-04-29T02:31:00+10:00">N</element>
        </level>
      </period>
    </station>
    <station wmo-id="94872" bom-id="086266" tz="Australia/Melbourne" stn-name="FERNY CREEK" stn-height="512.90" type="AWS" lat="-37.8748" lon="145.3497" forecast-district-id="VIC_PW007" description="Ferny Creek">
      <period index="0" time-utc="2024-04-28T17:40:00+00:00" time-local="2024-04-29T03:40:00+10:00" wind-src="OMD">
        <level index="0" type="surface">
          <element units="Celsius" type="apparent_temp">10.3</element>
          <element units="Celsius" type="delta_t">5.4</element>
          <element units="km/h" type="gust_kmh">13</element>
          <element units="knots" type="wind_gust_spd">7</element>
          <element units="Celsius" type="air_temperature">13.4</element>
          <element units="Celsius" type="dew_point">1.1</element>
          <element units="%" type="rel-humidity">43</element>
          <element type="wind_dir">WNW</element>
          <element units="deg" type="wind_dir_deg">303</element>
          <element units="km/h" type="wind_spd_kmh">7</element>
          <element units="knots" type="wind_spd">4</element>
          <element start-time-local="2024-04-28T09:00:00+10:00" end-time-local="2024-04-29T03:42:00+10:00" duration="1122" start-time-utc="2024-04-27T23:00:00+00:00" end-time-utc="2024-04-28T17:42:00+00:00" units="mm" type="rainfall">0.0</element>
          <element start-time-local="2024-04-27T09:00:00+10:00" end-time-local="2024-04-28T09:00:00+10:00" duration="1440" start-time-utc="2024-04-26T23:00:00+00:00" end-time-utc="2024-04-27T23:00:00+00:00" units="mm" type="rainfall_24hr">0.0</element>
          <element start-time-local="2024-04-28T06:00:00+10:00" end-time-local="2024-04-28T21:00:00+10:00" start-time-utc="2024-04-27T20:00:00+00:00" end-time-utc="2024-04-28T11:00:00+00:00" units="Celsius" type="maximum_air_temperature" instance="running" time-utc="2024-04-28T04:22:00+00:00" time-local="2024-04-28T14:22:00+10:00">18.1</element>
          <element start-time-local="2024-04-28T18:00:00+10:00" end-time-local="2024-04-29T09:00:00+10:00" start-time-utc="2024-04-28T08:00:00+00:00" end-time-utc="2024-04-28T23:00:00+00:00" units="Celsius" type="minimum_air_temperature" instance="running" time-utc="2024-04-28T15:20:00+00:00" time-local="2024-04-29T01:20:00+10:00">12.9</element>
          <element start-time-local="2024-04-29T00:00:00+10:00" end-time-local="2024-04-30T00:00:00+10:00" start-time-utc="2024-04-28T14:00:00+00:00" end-time-utc="2024-04-29T14:00:00+00:00" units="knots" type="maximum_gust_spd" instance="running" time-utc="2024-04-28T17:02:00+00:00" time-local="2024-04-29T03:02:00+10:00">10</element>
          <element start-time-local="2024-04-29T00:00:00+10:00" end-time-local="2024-04-30T00:00:00+10:00" start-time-utc="2024-04-28T14:00:00+00:00" end-time-utc="2024-04-29T14:00:00+00:00" units="km/h" type="maximum_gust_kmh" instance="running" time-utc="2024-04-28T17:02:00+00:00" time-local="2024-04-29T03:02:00+10:00">19</element>
          <element start-time-local="2024-04-29T00:00:00+10:00" end-time-local="2024-04-30T00:00:00+10:00" start-time-utc="2024-04-28T14:00:00+00:00" end-time-utc="2024-04-29T14:00:00+00:00" type="maximum_gust_dir" i